Metadata-Version: 2.1
Name: probator-auditor-iam
Version: 1.0.2
Summary: IAM Policy and Role auditor
Home-page: https://github.com/bunjiboys/probator-auditor-iam/
Author: Asbjorn Kjaer
Author-email: bunjiboys+probator@gmail.com
License: License :: OSI Approved :: Apache Software License
Keywords: cloud security
Platform: UNKNOWN
Classifier: Development Status :: 4 - Beta
Classifier: Intended Audience :: System Administrators
Classifier: Intended Audience :: Information Technology
Classifier: License :: OSI Approved :: Apache Software License
Classifier: Programming Language :: Python :: 3.7
Classifier: Framework :: Flask
Classifier: Framework :: Sphinx
Classifier: Operating System :: MacOS :: MacOS X
Classifier: Operating System :: POSIX :: Linux
Classifier: Operating System :: Unix
Classifier: Environment :: Console
Classifier: Natural Language :: English
Classifier: Topic :: Security
Classifier: Topic :: Utilities
Requires-Python: ~=3.7
Provides-Extra: dev
Provides-Extra: test
